stm32ctl/__main__.py
stm32ctl/connection.py
stm32ctl/__init__.py
stm32ctl/client.py
stm32ctl/args.py
stm32ctl/main.py
stm32ctl-0.1.0.dist-info/LICENSE
stm32ctl-0.1.0.dist-info/entry_points.txt
stm32ctl-0.1.0.dist-info/METADATA
stm32ctl-0.1.0.dist-info/WHEEL
stm32ctl-0.1.0.dist-info/RECORD
