Metadata-Version: 2.1
Name: stm32ctl
Version: 0.1.0
Summary: STM32 system bootloader control
Author: Bozo Kopic
Author-email: "Bozo Kopic" <bozo@kopic.xyz>
License: GPLv3
Classifier: Programming Language :: Python :: 3
Classifier: License :: OSI Approved :: GNU General Public License v3 (GPLv3)
Provides-Extra: dev
Requires-Dist: hat-aio ~=0.7.8
Requires-Dist: hat-drivers ~=0.7.8
Requires-Dist: mkwhl ~=0.2.6; extra == 'dev'
Requires-Python: >=3.10
Project-URL: Repository, https://github.com/bozokopic/stm32ctl.git
